thaitaxrefund/__init__.py
thaitaxrefund-0.4.5.data/scripts/thaitaxrefund
thaitaxrefund-0.4.5.dist-info/LICENSE
thaitaxrefund-0.4.5.dist-info/METADATA
thaitaxrefund-0.4.5.dist-info/WHEEL
thaitaxrefund-0.4.5.dist-info/top_level.txt
thaitaxrefund-0.4.5.dist-info/RECORD
