Metadata-Version: 2.1
Name: thaitaxrefund
Version: 0.4.5
Summary: Thai tax refund checker
Home-page: https://github.com/kittinan/thai-tax-refund
Author: Kittinan Srithaworn
License: MIT
Project-URL: Bug Reports, https://github.com/kittinan/thai-tax-refund/issues
Project-URL: Source, https://github.com/kittinan/thai-tax-refund
Keywords: thai tax refund
Platform: UNKNOWN
Classifier: Programming Language :: Python :: 3
Classifier: License :: OSI Approved :: MIT License
Classifier: Operating System :: OS Independent
Requires-Dist: requests
Requires-Dist: docopt
